{"width":"80","height":"25","timeline":[{"d":[["r","bash-3.2$                                                                       "],["a"," "],"d","d","d","d","d","d","d","d","d","d","d","d","d","d","d","d","d","d","d","d","d","d","d"],"x":11,"B":[["a","0"],"d","d","d","d","d","d","d","d","d","d","d","d","d","d","d","d","d","d","d","d","d","d","d","d"],"y":1,"b":[["a","0"],"d","d","d","d","d","d","d","d","d","d","d","d","d","d","d","d","d","d","d","d","d","d","d","d"],"f":[["a","7"],"d","d","d","d","d","d","d","d","d","d","d","d","d","d","d","d","d","d","d","d","d","d","d","d"],"U":[["a","0"],"d","d","d","d","d","d","d","d","d","d","d","d","d","d","d","d","d","d","d","d","d","d","d","d"],"t":1305092002.9374,"i":1},{"y":1,"d":[[0,10,"c"]],"x":12,"t":1305092003.82487},{"y":1,"d":[[0,11,"d"]],"x":13,"t":1305092003.99267},{"y":1,"x":14,"t":1305092004.08072},{"y":1,"d":[[0,13,"/"]],"x":15,"t":1305092004.21655},{"y":1,"d":[[0,14,"p"]],"x":16,"t":1305092004.40084},{"y":1,"d":[[0,15,"a"]],"x":17,"t":1305092004.44885},{"y":1,"d":[[0,16,"t"]],"x":18,"t":1305092004.54466},{"y":1,"d":[[0,17,"h"]],"x":19,"t":1305092004.61689},{"y":1,"d":[[0,18,"/"]],"x":20,"t":1305092004.77565},{"y":1,"d":[[0,19,"t"]],"x":21,"t":1305092005.00046},{"y":1,"d":[[0,20,"o"]],"x":22,"t":1305092005.08865},{"y":1,"d":[[0,21,"/"]],"x":23,"t":1305092005.22336},{"y":1,"d":[[0,22,"m"]],"x":24,"t":1305092006.08866},{"y":1,"d":[[0,23,"y"]],"x":25,"t":1305092006.26487},{"y":1,"d":[[0,24,"/"]],"x":26,"t":1305092006.38328},{"y":1,"d":[[0,25,"w"]],"x":27,"t":1305092006.8646},{"y":1,"d":[[0,26,"o"]],"x":28,"t":1305092006.98453},{"y":1,"d":[[0,27,33,"rkspace"]],"x":35,"t":1305092007.08703},{"y":1,"d":[[0,34,"/"]],"x":36,"t":1305092007.68093},{"y":1,"d":[[0,35,"d"]],"x":37,"t":1305092007.91265},{"y":1,"d":[[0,36,"e"]],"x":38,"t":1305092008.07249},{"y":1,"d":[[0,37,"m"]],"x":39,"t":1305092008.18458},{"y":1,"d":[[0,38,"o"]],"x":40,"t":1305092008.29663},{"y":2,"x":1,"t":1305092008.52846},{"y":2,"d":[[1,0,8,"bash-3.2$"]],"x":11,"t":1305092008.52876},{"y":2,"d":[[1,10,"g"]],"x":12,"t":1305092009.03259},{"y":2,"d":[[1,11,"i"]],"x":13,"t":1305092009.11277},{"y":2,"d":[[1,12,"t"]],"x":14,"t":1305092009.22446},{"y":2,"x":15,"t":1305092009.25662},{"y":2,"d":[[1,14,"l"]],"x":16,"t":1305092009.33639},{"y":2,"d":[[1,15,"o"]],"x":17,"t":1305092009.52058},{"y":2,"d":[[1,16,"g"]],"x":18,"t":1305092009.68049},{"y":2,"x":19,"t":1305092009.83275},{"y":2,"d":[[1,18,"-"]],"x":20,"t":1305092010.08054},{"y":2,"d":[[1,19,"-"]],"x":21,"t":1305092010.26458},{"y":2,"d":[[1,20,"s"]],"x":22,"t":1305092010.38423},{"y":2,"d":[[1,21,"t"]],"x":23,"t":1305092010.50457},{"y":2,"d":[[1,22,"a"]],"x":24,"t":1305092010.63241},{"y":2,"d":[[1,23,"t"]],"x":25,"t":1305092010.7286},{"y":3,"x":1,"t":1305092010.79712},{"y":17,"d":[[2,0,46,"commit 61b1516058bd2359f99437d28a6b9fd6e933b001"],[3,0,37,"Author: Jiang Xin <jiangxin@ossxp.com>"],[4,0,37,"Date:   Wed May 11 11:33:44 2011 +0800"],[6,4,19,"who does commit?"],[8,0,46,"commit 38690158d57ea02061e42ab88101ed3517a4292f"],["cp",3,9],[10,0,37,"Date:   Wed May 11 11:03:28 2011 +0800"],[12,4,14,"intialized."],[14,1,13,"welcome.txt |"],[14,18,20,"1 +"],[15,1,48,"1 files changed, 1 insertions(+), 0 deletions(-)"],[16,0,8,"bash-3.2$"]],"x":11,"f":[[2,0,46,["a","3"]],["cp",2,8],[14,20,"2"]],"t":1305092010.80495},{"y":17,"d":[[16,10,"e"]],"x":12,"t":1305092016.46447},{"y":17,"d":[[16,11,"c"]],"x":13,"t":1305092016.64049},{"y":17,"d":[[16,12,"h"]],"x":14,"t":1305092016.72812},{"y":17,"d":[[16,13,"o"]],"x":15,"t":1305092016.82428},{"y":17,"x":16,"t":1305092017.00024},{"y":17,"d":[[16,15,"N"]],"x":17,"t":1305092018.26417},{"y":17,"d":[[16,16,"c"]],"x":18,"t":1305092018.56837},{"y":17,"d":[[16,16," "]],"x":17,"t":1305092019.04799},{"y":17,"d":[[16,16,"i"]],"x":18,"t":1305092019.26497},{"y":17,"d":[[16,17,"c"]],"x":19,"t":1305092019.35997},{"y":17,"d":[[16,18,"e"]],"x":20,"t":1305092019.55196},{"y":17,"x":21,"t":1305092020.44069},{"y":17,"d":[[16,20,"t"]],"x":22,"t":1305092020.61625},{"y":17,"d":[[16,21,"o"]],"x":23,"t":1305092020.66388},{"y":17,"x":24,"t":1305092020.79991},{"y":17,"d":[[16,23,"m"]],"x":25,"t":1305092020.99189},{"y":17,"d":[[16,24,"e"]],"x":26,"t":1305092021.08012},{"y":17,"d":[[16,25,"e"]],"x":27,"t":1305092021.25577},{"y":17,"d":[[16,26,"t"]],"x":28,"t":1305092021.64785},{"y":17,"x":29,"t":1305092021.83984},{"y":17,"d":[[16,28,"y"]],"x":30,"t":1305092021.99186},{"y":17,"d":[[16,29,"o"]],"x":31,"t":1305092022.10377},{"y":17,"d":[[16,30,"u"]],"x":32,"t":1305092022.18382},{"y":17,"d":[[16,31,"."]],"x":33,"t":1305092022.79231},{"y":17,"x":34,"t":1305092022.9918},{"y":17,"d":[[16,33,">"]],"x":35,"t":1305092023.26416},{"y":17,"d":[[16,34,">"]],"x":36,"t":1305092023.43167},{"y":17,"x":37,"t":1305092023.64792},{"y":17,"d":[[16,36,"w"]],"x":38,"t":1305092023.90375},{"y":17,"d":[[16,37,"e"]],"x":39,"t":1305092024.05568},{"y":17,"d":[[16,38,46,"lcome.txt"]],"x":49,"t":1305092024.2799},{"y":18,"x":1,"t":1305092024.48774},{"y":18,"d":[[17,0,8,"bash-3.2$"]],"x":11,"t":1305092024.48809},{"y":18,"d":[[17,10,"g"]],"x":12,"t":1305092024.93552},{"y":18,"d":[[17,11,"i"]],"x":13,"t":1305092025.01558},{"y":18,"d":[[17,12,"t"]],"x":14,"t":1305092025.13585},{"y":18,"x":15,"t":1305092025.18378},{"y":18,"d":[[17,14,"s"]],"x":16,"t":1305092025.4157},{"y":18,"d":[[17,15,"t"]],"x":17,"t":1305092025.58404},{"y":18,"d":[[17,16,"a"]],"x":18,"t":1305092025.67172},{"y":18,"d":[[17,17,"t"]],"x":19,"t":1305092025.79982},{"y":18,"d":[[17,18,"u"]],"x":20,"t":1305092025.89562},{"y":18,"d":[[17,19,"s"]],"x":21,"t":1305092025.99177},{"y":19,"x":1,"t":1305092026.23166},{"y":25,"d":[["cp",2,0],["cp",3,1],["cp",4,2],["cp",5,3],["cp",6,4],["cp",8,6],["cp",1,7],["cp",10,8],["cp",3,9],["cp",12,10],["cp",14,12],["cp",15,13],["cp",16,14],["cp",17,15],[16,0,46,"# On branch master                             "],[17,0,11,"# Changes no"],[17,17,31,"ged for commit:"],[18,0,61,"#   (use \"git add <file>...\" to update what will be committed)"],[19,0,76,"#   (use \"git checkout -- <file>...\" to discard changes in working directory)"],[20,0,"#"],[21,0,"#"],[21,8,30,"modified:   welcome.txt"],["cp",20,22],[23,0,64,"no changes added to commit (use \"git add\" and/or \"git commit -a\")"],[24,0,8,"bash-3.2$"]],"x":11,"f":[["cp",2,0],["cp",1,2],["cp",0,6],["cp",1,8],["cp",14,12],["cp",1,14],[21,8,30,["a","1"]]],"t":1305092026.2401},{"y":25,"d":[[24,10,"g"]],"x":12,"t":1305092026.83171},{"y":25,"d":[[24,11,"i"]],"x":13,"t":1305092026.91176},{"y":25,"d":[[24,12,"t"]],"x":14,"t":1305092027.02366},{"y":25,"x":15,"t":1305092027.07953},{"y":25,"d":[[24,14,"d"]],"x":16,"t":1305092027.20744},{"y":25,"d":[[24,15,"i"]],"x":17,"t":1305092027.26415},{"y":25,"d":[[24,16,"f"]],"x":18,"t":1305092027.40763},{"y":25,"d":[[24,17,"f"]],"x":19,"t":1305092027.5679},{"y":25,"d":[["cp",1,0],["cp",2,1],["cp",3,2],["cp",4,3],["cp",2,4],["cp",6,5],["cp",0,6],["cp",8,7],["cp",2,8],["cp",10,9],["cp",2,10],["cp",12,11],["cp",13,12],["cp",14,13],["cp",15,14],["cp",16,15],["cp",17,16],["cp",18,17],["cp",19,18],["cp",20,19],["cp",21,20],["cp",19,21],["cp",23,22],["cp",24,23],["cp",2,24]],"x":1,"f":[["cp",1,0],["cp",6,5],["cp",0,6],["cp",12,11],["cp",0,12],["cp",21,20],["cp",0,21]],"t":1305092027.64737},{"y":25,"d":[["cp",7,0],["cp",2,1],["cp",9,2],["cp",1,3],["cp",11,4],["cp",12,5],["cp",13,6],["cp",14,7],["cp",15,8],["cp",16,9],["cp",17,10],["cp",18,11],["cp",19,12],["cp",20,13],["cp",12,14],["cp",22,15],["cp",23,16],[17,0,61,"diff --git a/welcome.txt b/welcome.txt                        "],[18,0,76,"index 18832d3..fd3c069 100644                                                "],[19,0,16,"--- a/welcome.txt"],[20,0,30,"+++ b/welcome.txt              "],[21,0,12,"@@ -1 +1,2 @@"],[22,0,64," Hello.                                                          "],[23,0,17,"+Nice to meet you."],[24,0,8,"bash-3.2$"]],"x":11,"f":[["cp",11,4],["cp",0,5],["cp",0,11],["cp",20,13],["cp",0,20],[21,0,12,["a","6"]],[23,0,17,["a","2"]]],"B":[[17,0,37,["a","1"]],[18,0,28,["a","1"]],[19,0,16,["a","1"]],["cp",19,20]],"t":1305092027.65936},{"y":25,"d":[[24,10,"g"]],"x":12,"t":1305092030.62358},{"y":25,"d":[[24,11,"i"]],"x":13,"t":1305092030.73556},{"y":25,"d":[[24,12,"t"]],"x":14,"t":1305092030.79926},{"d":[["r","Date:   Wed May 11 11:03:28 2011 +0800                                          "],["a"," "],["r","    intialized.                                                                 "],["a"," "],["r"," welcome.txt |    1 +                                                           "],["r"," 1 files changed, 1 insertions(+), 0 deletions(-)                               "],["r","bash-3.2$ echo Nice to meet you. >> welcome.txt                                 "],["r","bash-3.2$ git status                                                            "],["r","# On branch master                                                              "],["r","# Changes not staged for commit:                                                "],["r","#   (use \"git add <file>...\" to update what will be committed)                  "],["r","#   (use \"git checkout -- <file>...\" to discard changes in working directory)   "],["r","#                                                                               "],["r","#       modified:   welcome.txt                                                 "],["r","#                                                                               "],["r","no changes added to commit (use \"git add\" and/or \"git commit -a\")               "],["r","bash-3.2$ git diff                                                              "],["r","diff --git a/welcome.txt b/welcome.txt                                          "],["r","index 18832d3..fd3c069 100644                                                   "],["r","--- a/welcome.txt                                                               "],["r","+++ b/welcome.txt                                                               "],["r","@@ -1 +1,2 @@                                                                   "],["r"," Hello.                                                                         "],["r","+Nice to meet you.                                                              "],["r","bash-3.2$ git                                                                   "]],"x":15,"B":[["a","0"],"d","d","d","d","d","d","d","d","d","d","d","d","d","d","d","d",["r","11111111111111111111111111111111111111000000000000000000000000000000000000000000"],["r","11111111111111111111111111111000000000000000000000000000000000000000000000000000"],["r","11111111111111111000000000000000000000000000000000000000000000000000000000000000"],"d",["a","0"],"d","d","d"],"y":25,"b":[["a","0"],"d","d","d","d","d","d","d","d","d","d","d","d","d","d","d","d","d","d","d","d","d","d","d","d"],"f":[["a","7"],"d","d","d",["r","77777777777777777777277777777777777777777777777777777777777777777777777777777777"],["a","7"],"d","d","d","d","d","d","d",["r","77777777111111111111111111111117777777777777777777777777777777777777777777777777"],["a","7"],"d","d","d","d","d","d",["r","66666666666667777777777777777777777777777777777777777777777777777777777777777777"],["a","7"],["r","22222222222222222277777777777777777777777777777777777777777777777777777777777777"],["a","7"]],"U":[["a","0"],"d","d","d","d","d","d","d","d","d","d","d","d","d","d","d","d","d","d","d","d","d","d","d","d"],"t":1305092030.87936,"i":1},{"y":25,"d":[[24,14,"c"]],"x":16,"t":1305092031.02364},{"y":25,"d":[[24,15,"o"]],"x":17,"t":1305092031.07153},{"y":25,"d":[[24,16,"m"]],"x":18,"t":1305092031.23936},{"y":25,"d":[[24,17,"m"]],"x":19,"t":1305092031.38348},{"y":25,"d":[[24,18,"i"]],"x":20,"t":1305092031.55938},{"y":25,"d":[[24,19,"t"]],"x":21,"t":1305092031.65532},{"y":25,"x":22,"t":1305092031.74357},{"y":25,"d":[[24,21,"-"]],"x":23,"t":1305092031.9112},{"y":25,"d":[[24,22,"m"]],"x":24,"t":1305092032.15946},{"y":25,"x":25,"t":1305092032.31924},{"y":25,"d":[[24,24,"\""]],"x":26,"t":1305092032.85533},{"y":25,"d":[[24,25,"A"]],"x":27,"t":1305092033.33524},{"y":25,"d":[[24,26,"p"]],"x":28,"t":1305092033.58345},{"y":25,"d":[[24,27,"p"]],"x":29,"t":1305092033.72729},{"y":25,"d":[[24,28,"e"]],"x":30,"t":1305092033.87917},{"y":25,"d":[[24,29,"n"]],"x":31,"t":1305092033.99933},{"y":25,"d":[[24,30,"d"]],"x":32,"t":1305092034.10322},{"y":25,"x":33,"t":1305092034.5752},{"y":25,"d":[[24,32,"a"]],"x":34,"t":1305092035.07104},{"y":25,"x":35,"t":1305092035.20722},{"y":25,"d":[[24,34,"n"]],"x":36,"t":1305092035.37503},{"y":25,"d":[[24,35,"i"]],"x":37,"t":1305092035.50334},{"y":25,"d":[[24,36,"c"]],"x":38,"t":1305092035.62353},{"y":25,"d":[[24,37,"e"]],"x":39,"t":1305092035.79918},{"y":25,"x":40,"t":1305092035.97495},{"y":25,"d":[[24,39,"l"]],"x":41,"t":1305092036.10343},{"y":25,"d":[[24,40,"i"]],"x":42,"t":1305092036.23913},{"y":25,"d":[[24,41,"n"]],"x":43,"t":1305092036.37524},{"y":25,"d":[[24,42,"e"]],"x":44,"t":1305092036.519},{"y":25,"d":[[24,43,"."]],"x":45,"t":1305092036.67108},{"y":25,"d":[[24,44,"\""]],"x":46,"t":1305092037.71124},{"y":25,"d":[["cp",1,0],["cp",2,1],["cp",0,2],["cp",4,3],["cp",5,4],["cp",6,5],["cp",7,6],["cp",8,7],["cp",9,8],["cp",10,9],["cp",11,10],["cp",12,11],["cp",13,12],["cp",11,13],["cp",15,14],["cp",16,15],["cp",17,16],["cp",18,17],["cp",19,18],["cp",20,19],["cp",21,20],["cp",22,21],["cp",23,22],["cp",24,23],["cp",0,24]],"x":1,"f":[["cp",4,3],["cp",0,4],["cp",13,12],["cp",0,13],["cp",21,20],["cp",0,21],["cp",23,22],["cp",0,23]],"B":[["cp",17,16],["cp",18,17],["cp",19,18],["cp",0,20]],"t":1305092038.47098},{"y":25,"d":[["cp",8,0],["cp",9,1],["cp",10,2],["cp",11,3],["cp",12,4],["cp",3,5],["cp",14,6],["cp",15,7],["cp",16,8],["cp",17,9],["cp",18,10],["cp",19,11],["cp",20,12],["cp",21,13],["cp",22,14],["cp",23,15],[16,0,37,"# On branch master                    "],["cp",0,17],["cp",1,18],["cp",2,19],["cp",3,20],["cp",4,21],["cp",3,22],["cp",6,23],[24,0,8,"bash-3.2$"]],"x":11,"f":[["cp",0,3],["cp",12,4],["cp",20,12],["cp",22,14],["cp",0,20],["cp",4,21],["cp",0,22]],"B":[["cp",16,8],["cp",17,9],["cp",18,10],["cp",10,11],["cp",0,16],["cp",0,17],["cp",0,18],["cp",0,19]],"t":1305092038.48097},{"y":25,"d":[[24,10,"g"]],"x":12,"t":1305092040.80686},{"y":25,"d":[[24,11,"i"]],"x":13,"t":1305092040.871},{"y":25,"d":[[24,12,"t"]],"x":14,"t":1305092041.00698},{"y":25,"x":15,"t":1305092041.06387},{"y":25,"d":[[24,14,"l"]],"x":16,"t":1305092041.17482},{"y":25,"d":[[24,15,"o"]],"x":17,"t":1305092041.35983},{"y":25,"d":[[24,16,"g"]],"x":18,"t":1305092041.44692},{"y":25,"x":19,"t":1305092041.52682},{"y":25,"d":[[24,18,"-"]],"x":20,"t":1305092041.7831},{"y":25,"d":[[24,19,"-"]],"x":21,"t":1305092041.98297},{"y":25,"d":[[24,20,"p"]],"x":22,"t":1305092043.01487},{"y":25,"d":[[24,21,"r"]],"x":23,"t":1305092043.11874},{"y":25,"d":[[24,22,"e"]],"x":24,"t":1305092043.27891},{"y":25,"d":[[24,23,"t"]],"x":25,"t":1305092043.51913},{"y":25,"d":[[24,24,"t"]],"x":26,"t":1305092043.67908},{"y":25,"d":[[24,25,"y"]],"x":27,"t":1305092043.83066},{"y":25,"d":[[24,26,"="]],"x":28,"t":1305092044.15066},{"y":25,"d":[[24,27,"o"]],"x":29,"t":1305092044.4548},{"y":25,"d":[[24,28,"n"]],"x":30,"t":1305092044.59904},{"y":25,"d":[[24,29,"e"]],"x":31,"t":1305092044.71061},{"y":25,"d":[[24,30,"l"]],"x":32,"t":1305092044.80787},{"y":25,"d":[[24,31,"i"]],"x":33,"t":1305092044.98284},{"y":25,"d":[[24,32,"n"]],"x":34,"t":1305092045.08681},{"y":25,"d":[[24,33,"e"]],"x":35,"t":1305092045.16662},{"y":25,"d":[["cp",1,0],["cp",2,1],["cp",3,2],["cp",4,3],["cp",2,4],["cp",6,5],["cp",7,6],["cp",8,7],["cp",9,8],["cp",10,9],["cp",11,10],["cp",12,11],["cp",13,12],["cp",14,13],["cp",15,14],["cp",16,15],["cp",17,16],["cp",0,17],["cp",1,18],["cp",2,19],["cp",3,20],["cp",2,21],["cp",5,22],["cp",24,23],[24,["a"," "]]],"x":1,"f":[["cp",4,3],["cp",0,4],["cp",12,11],["cp",0,12],["cp",14,13],["cp",0,14],["cp",3,20],["cp",0,21]],"B":[["cp",8,7],["cp",9,8],["cp",10,9],["cp",0,11]],"t":1305092045.31057},{"y":25,"d":[["cp",2,0],["cp",3,1],["cp",5,3],["cp",6,4],["cp",7,5],["cp",8,6],["cp",9,7],["cp",10,8],["cp",11,9],["cp",12,10],["cp",13,11],["cp",14,12],["cp",15,13],["cp",16,14],["cp",17,15],["cp",18,16],["cp",0,17],["cp",1,18],["cp",3,20],["cp",23,21],[22,0,64,"61b1516058bd2359f99437d28a6b9fd6e933b001 who does commit?        "],[23,0,51,"38690158d57ea02061e42ab88101ed3517a4292f intialized."],[24,0,8,"bash-3.2$"]],"x":11,"f":[["cp",3,1],["cp",0,3],["cp",11,9],["cp",13,11],["cp",0,13],["cp",1,18],["cp",0,20],[22,0,39,["a","3"]],["cp",22,23]],"B":[["cp",7,5],["cp",8,6],["cp",9,7],["cp",7,8],["cp",0,9],["cp",0,10]],"t":1305092045.32237},{"y":25,"d":[[24,10,"g"]],"x":12,"t":1305092045.72689},{"y":25,"d":[[24,11,"i"]],"x":13,"t":1305092045.7907},{"y":25,"d":[[24,12,"t"]],"x":14,"t":1305092045.90279},{"y":25,"x":15,"t":1305092045.95878},{"y":25,"d":[[24,14,"l"]],"x":16,"t":1305092046.51077},{"y":25,"d":[[24,15,"o"]],"x":17,"t":1305092046.67062},{"y":25,"d":[[24,16,"g"]],"x":18,"t":1305092046.77462},{"y":25,"x":19,"t":1305092046.83095},{"y":25,"d":[[24,18,"-"]],"x":20,"t":1305092047.04656},{"y":25,"d":[[24,19,"-"]],"x":21,"t":1305092047.24652},{"y":25,"d":[[24,20,"o"]],"x":22,"t":1305092047.42263},{"y":25,"d":[[24,21,"n"]],"x":23,"t":1305092047.55854},{"y":25,"d":[[24,22,"e"]],"x":24,"t":1305092047.60649},{"y":25,"d":[[24,23,"l"]],"x":25,"t":1305092047.75054},{"y":25,"d":[[24,24,"i"]],"x":26,"t":1305092047.89455},{"y":25,"d":[[24,25,"n"]],"x":27,"t":1305092048.02297},{"y":25,"d":[[24,26,"e"]],"x":28,"t":1305092048.13469},{"y":25,"d":[["cp",1,0],["cp",2,1],["cp",3,2],["cp",4,3],["cp",5,4],["cp",6,5],["cp",7,6],["cp",8,7],["cp",9,8],["cp",10,9],["cp",11,10],["cp",12,11],["cp",13,12],["cp",14,13],["cp",15,14],["cp",16,15],["cp",1,16],["cp",0,17],["cp",1,18],["cp",2,19],["cp",21,20],["cp",22,21],["cp",23,22],["cp",24,23],[24,["a"," "]]],"x":1,"f":[["cp",1,0],["cp",2,1],["cp",9,8],["cp",1,9],["cp",11,10],["cp",1,11],["cp",0,17],["cp",1,18],["cp",22,21],["cp",1,23]],"B":[["cp",5,4],["cp",6,5],["cp",7,6],["cp",0,8]],"t":1305092048.28019},{"y":25,"d":[["cp",2,0],["cp",3,1],["cp",4,2],["cp",5,3],["cp",6,4],["cp",7,5],["cp",8,6],["cp",9,7],["cp",10,8],["cp",11,9],["cp",12,10],["cp",13,11],["cp",14,12],["cp",15,13],["cp",16,14],["cp",17,15],["cp",0,17],["cp",20,18],["cp",21,19],["cp",22,20],["cp",23,21],[22,0,51,"61b1516 who does commit?                            "],[23,0,26,"3869015 intialized.        "],[24,0,8,"bash-3.2$"]],"x":11,"f":[["cp",1,0],["cp",8,6],["cp",10,8],["cp",0,10],["cp",17,15],["cp",0,17],["cp",21,19],["cp",19,20],["cp",0,21],[22,7,39,["a","7"]],["cp",22,23]],"B":[["cp",4,2],["cp",5,3],["cp",6,4],["cp",4,5],["cp",0,6],["cp",0,7]],"t":1305092048.29132},{"y":25,"d":[[24,10,"g"]],"x":12,"t":1305092051.60657},{"y":25,"d":[[24,11,"i"]],"x":13,"t":1305092051.70224},{"y":25,"d":[[24,12,"t"]],"x":14,"t":1305092051.8065},{"y":25,"x":15,"t":1305092051.91044},{"y":25,"d":[[24,14,"s"]],"x":16,"t":1305092052.07171},{"y":25,"d":[[24,15,"t"]],"x":17,"t":1305092052.21432},{"y":25,"d":[[24,16,"a"]],"x":18,"t":1305092052.39028},{"y":25,"d":[[24,17,"t"]],"x":19,"t":1305092052.49439},{"y":25,"d":[[24,18,"u"]],"x":20,"t":1305092052.63042},{"y":25,"d":[[24,19,"s"]],"x":21,"t":1305092052.70234},{"y":25,"x":22,"t":1305092052.83828},{"y":25,"d":[[24,21,"-"]],"x":23,"t":1305092052.93458},{"y":25,"d":[[24,22,"s"]],"x":24,"t":1305092053.07839},{"y":25,"d":[["cp",1,0],["cp",2,1],["cp",3,2],["cp",4,3],["cp",5,4],["cp",6,5],["cp",7,6],["cp",8,7],["cp",9,8],["cp",10,9],["cp",11,10],["cp",12,11],["cp",13,12],["cp",14,13],["cp",15,14],["cp",13,15],["cp",17,16],["cp",18,17],["cp",19,18],["cp",20,19],["cp",21,20],["cp",22,21],["cp",23,22],["cp",24,23],[24,["a"," "]]],"x":1,"f":[["cp",6,5],["cp",0,6],["cp",8,7],["cp",0,8],["cp",15,14],["cp",0,15],["cp",19,18],["cp",0,20],["cp",22,21],["cp",0,23]],"B":[["cp",2,1],["cp",3,2],["cp",4,3],["cp",0,5]],"t":1305092053.21425},{"y":25,"d":[["cp",1,0],["cp",2,1],["cp",3,2],["cp",4,3],["cp",5,4],["cp",6,5],["cp",7,6],["cp",8,7],["cp",9,8],["cp",10,9],["cp",11,10],["cp",12,11],["cp",13,12],["cp",14,13],["cp",12,14],["cp",16,15],["cp",17,16],["cp",18,17],["cp",19,18],["cp",20,19],["cp",21,20],["cp",22,21],["cp",23,22],[23,0,22," M welcome.txt         "],[24,0,8,"bash-3.2$"]],"x":11,"f":[["cp",5,4],["cp",0,5],["cp",7,6],["cp",0,7],["cp",14,13],["cp",0,14],["cp",18,17],["cp",0,19],["cp",21,20],["cp",0,22],[23,1,"1"]],"B":[["cp",1,0],["cp",2,1],["cp",3,2],["cp",5,4]],"t":1305092053.22631},{"y":25,"d":[[24,10,"g"]],"x":12,"t":1305092055.06237},{"y":25,"d":[[24,11,"i"]],"x":13,"t":1305092055.25413},{"y":25,"d":[[24,12,"t"]],"x":14,"t":1305092055.42224},{"y":25,"x":15,"t":1305092055.48644},{"y":25,"d":[[24,14,"a"]],"x":16,"t":1305092057.61422},{"y":25,"d":[[24,15,"d"]],"x":17,"t":1305092057.78197},{"d":[["r","diff --git a/welcome.txt b/welcome.txt                                          "],["r","index 18832d3..fd3c069 100644                                                   "],["r","--- a/welcome.txt                                                               "],["r","+++ b/welcome.txt                                                               "],["r","@@ -1 +1,2 @@                                                                   "],["r"," Hello.                                                                         "],["r","+Nice to meet you.                                                              "],["r","bash-3.2$ git commit -m \"Append a nice line.\"                                   "],["r","# On branch master                                                              "],["r","# Changes not staged for commit:                                                "],["r","#   (use \"git add <file>...\" to update what will be committed)                  "],["r","#   (use \"git checkout -- <file>...\" to discard changes in working directory)   "],["r","#                                                                               "],["r","#       modified:   welcome.txt                                                 "],["r","#                                                                               "],["r","no changes added to commit (use \"git add\" and/or \"git commit -a\")               "],["r","bash-3.2$ git log --pretty=oneline                                              "],["r","61b1516058bd2359f99437d28a6b9fd6e933b001 who does commit?                       "],["r","38690158d57ea02061e42ab88101ed3517a4292f intialized.                            "],["r","bash-3.2$ git log --oneline                                                     "],["r","61b1516 who does commit?                                                        "],["r","3869015 intialized.                                                             "],["r","bash-3.2$ git status -s                                                         "],["r"," M welcome.txt                                                                  "],["r","bash-3.2$ git add                                                               "]],"x":18,"B":[["r","11111111111111111111111111111111111111000000000000000000000000000000000000000000"],["r","11111111111111111111111111111000000000000000000000000000000000000000000000000000"],["r","11111111111111111000000000000000000000000000000000000000000000000000000000000000"],"d",["a","0"],"d","d","d","d","d","d","d","d","d","d","d","d","d","d","d","d","d","d","d","d"],"y":25,"b":[["a","0"],"d","d","d","d","d","d","d","d","d","d","d","d","d","d","d","d","d","d","d","d","d","d","d","d"],"f":[["a","7"],"d","d","d",["r","66666666666667777777777777777777777777777777777777777777777777777777777777777777"],["a","7"],["r","22222222222222222277777777777777777777777777777777777777777777777777777777777777"],["a","7"],"d","d","d","d","d",["r","77777777111111111111111111111117777777777777777777777777777777777777777777777777"],["a","7"],"d","d",["r","33333333333333333333333333333333333333337777777777777777777777777777777777777777"],"d",["a","7"],["r","33333337777777777777777777777777777777777777777777777777777777777777777777777777"],"d",["a","7"],["r","71777777777777777777777777777777777777777777777777777777777777777777777777777777"],["a","7"]],"U":[["a","0"],"d","d","d","d","d","d","d","d","d","d","d","d","d","d","d","d","d","d","d","d","d","d","d","d"],"t":1305092057.95014,"i":1},{"y":25,"x":19,"t":1305092058.03823},{"y":25,"d":[[24,18,"w"]],"x":20,"t":1305092058.22212},{"y":25,"d":[[24,19,"e"]],"x":21,"t":1305092058.35811},{"y":25,"d":[[24,20,"l"]],"x":22,"t":1305092058.49415},{"y":25,"d":[[24,21,28,"come.txt"]],"x":30,"t":1305092058.63174},{"y":25,"d":[["cp",1,0],["cp",2,1],["cp",3,2],["cp",4,3],["cp",5,4],["cp",6,5],["cp",7,6],["cp",8,7],["cp",9,8],["cp",10,9],["cp",11,10],["cp",12,11],["cp",13,12],["cp",11,13],["cp",15,14],["cp",16,15],["cp",17,16],["cp",18,17],["cp",19,18],["cp",20,19],["cp",21,20],["cp",22,21],["cp",23,22],["cp",24,23],[24,["a"," "]]],"x":1,"f":[["cp",4,3],["cp",0,4],["cp",6,5],["cp",0,6],["cp",13,12],["cp",0,13],["cp",17,16],["cp",0,18],["cp",20,19],["cp",0,21],["cp",23,22],["cp",0,23]],"B":[["cp",1,0],["cp",2,1],["cp",4,3]],"t":1305092059.1099},{"y":25,"d":[[24,0,8,"bash-3.2$"]],"x":11,"t":1305092059.11816},{"y":25,"d":[[24,10,"g"]],"x":12,"t":1305092060.02222},{"y":25,"d":[[24,11,"i"]],"x":13,"t":1305092060.11788},{"y":25,"d":[[24,12,"t"]],"x":14,"t":1305092060.2301},{"y":25,"x":15,"t":1305092060.31802},{"y":25,"d":[[24,14,"s"]],"x":16,"t":1305092061.29399},{"y":25,"d":[[24,15,"t"]],"x":17,"t":1305092061.46985},{"y":25,"d":[[24,16,"a"]],"x":18,"t":1305092061.60575},{"y":25,"d":[[24,17,"t"]],"x":19,"t":1305092061.71008},{"y":25,"d":[[24,18,"u"]],"x":20,"t":1305092061.79801},{"y":25,"d":[[24,19,"s"]],"x":21,"t":1305092061.89397},{"y":25,"x":22,"t":1305092062.40578},{"y":25,"d":[[24,21,"-"]],"x":23,"t":1305092062.51787},{"y":25,"d":[["cp",21,24]],"x":24,"t":1305092062.64595},{"y":25,"d":[["cp",1,0],["cp",2,1],["cp",3,2],["cp",4,3],["cp",5,4],["cp",6,5],["cp",7,6],["cp",8,7],["cp",9,8],["cp",10,9],["cp",11,10],["cp",12,11],["cp",10,12],["cp",14,13],["cp",15,14],["cp",16,15],["cp",17,16],["cp",18,17],["cp",19,18],["cp",20,19],["cp",21,20],["cp",22,21],["cp",23,22],["cp",20,23],[24,["a"," "]]],"x":1,"f":[["cp",3,2],["cp",0,3],["cp",5,4],["cp",0,5],["cp",12,11],["cp",0,12],["cp",16,15],["cp",0,17],["cp",19,18],["cp",0,20],["cp",22,21],["cp",0,22]],"B":[["cp",1,0],["cp",3,2]],"t":1305092062.75781},{"y":25,"d":[["cp",1,0],["cp",2,1],["cp",3,2],["cp",4,3],["cp",5,4],["cp",6,5],["cp",7,6],["cp",8,7],["cp",9,8],["cp",10,9],["cp",11,10],["cp",9,11],["cp",13,12],["cp",14,13],["cp",15,14],["cp",16,15],["cp",17,16],["cp",18,17],["cp",19,18],["cp",20,19],["cp",21,20],["cp",22,21],["cp",19,22],[23,0,22,"M  welcome.txt         "],[24,0,8,"bash-3.2$"]],"x":11,"f":[["cp",2,1],["cp",0,2],["cp",4,3],["cp",0,4],["cp",11,10],["cp",0,11],["cp",15,14],["cp",0,16],["cp",18,17],["cp",0,19],["cp",21,20],["cp",0,21],[23,0,"2"]],"B":[["cp",2,1]],"t":1305092062.76687},{"y":25,"d":[[24,10,"g"]],"x":12,"t":1305092063.2789},{"y":25,"d":[[24,11,"i"]],"x":13,"t":1305092063.35798},{"y":25,"d":[[24,12,"t"]],"x":14,"t":1305092063.49405},{"y":25,"x":15,"t":1305092063.56567},{"y":25,"d":[[24,14,"d"]],"x":16,"t":1305092063.74985},{"y":25,"d":[[24,15,"i"]],"x":17,"t":1305092063.8297},{"y":25,"d":[[24,16,"f"]],"x":18,"t":1305092063.93366},{"y":25,"d":[[24,17,"f"]],"x":19,"t":1305092064.1189},{"y":25,"d":[["cp",1,0],["cp",2,1],["cp",3,2],["cp",4,3],["cp",5,4],["cp",6,5],["cp",7,6],["cp",8,7],["cp",9,8],["cp",10,9],["cp",8,10],["cp",12,11],["cp",13,12],["cp",14,13],["cp",15,14],["cp",16,15],["cp",17,16],["cp",18,17],["cp",19,18],["cp",20,19],["cp",21,20],["cp",18,21],["cp",23,22],["cp",24,23],[24,["a"," "]]],"x":1,"f":[["cp",1,0],["cp",2,1],["cp",3,2],["cp",1,3],["cp",10,9],["cp",1,10],["cp",14,13],["cp",1,15],["cp",17,16],["cp",1,18],["cp",20,19],["cp",1,20],["cp",23,22],["cp",1,23]],"B":[["cp",1,0]],"t":1305092064.21389},{"y":25,"d":[[24,0,8,"bash-3.2$"]],"x":11,"t":1305092064.22605},{"y":25,"d":[[24,10,"g"]],"x":12,"t":1305092065.14963},{"y":25,"d":[[24,11,"i"]],"x":13,"t":1305092065.25349},{"y":25,"d":[[24,12,"t"]],"x":14,"t":1305092065.34971},{"y":25,"x":15,"t":1305092065.40562},{"y":25,"d":[[24,14,"d"]],"x":16,"t":1305092065.59771},{"y":25,"d":[[24,15,"i"]],"x":17,"t":1305092065.69365},{"y":25,"d":[[24,16,"f"]],"x":18,"t":1305092065.8138},{"y":25,"d":[["cp",23,24]],"x":19,"t":1305092065.97363},{"y":25,"x":20,"t":1305092066.06178},{"y":25,"d":[[24,19,"-"]],"x":21,"t":1305092066.27761},{"y":25,"d":[["cp",23,24]],"x":20,"t":1305092066.74942},{"y":25,"d":[[24,19,"H"]],"x":21,"t":1305092067.12561},{"y":25,"d":[[24,20,"E"]],"x":22,"t":1305092067.19761},{"y":25,"d":[[24,21,"A"]],"x":23,"t":1305092067.34952},{"y":25,"d":[[24,22,"D"]],"x":24,"t":1305092067.45343},{"y":25,"d":[["cp",1,0],["cp",2,1],["cp",3,2],["cp",4,3],["cp",5,4],["cp",6,5],["cp",7,6],["cp",8,7],["cp",9,8],["cp",7,9],["cp",11,10],["cp",12,11],["cp",13,12],["cp",14,13],["cp",15,14],["cp",16,15],["cp",17,16],["cp",18,17],["cp",19,18],["cp",20,19],["cp",17,20],["cp",22,21],["cp",23,22],["cp",24,23],[24,["a"," "]]],"x":1,"f":[["cp",1,0],["cp",2,1],["cp",0,2],["cp",9,8],["cp",0,9],["cp",13,12],["cp",0,14],["cp",16,15],["cp",0,17],["cp",19,18],["cp",0,19],["cp",22,21],["cp",0,22]],"t":1305092068.1255},{"y":25,"d":[["cp",7,0],["cp",8,1],["cp",0,2],["cp",10,3],["cp",11,4],["cp",12,5],["cp",13,6],["cp",14,7],["cp",15,8],["cp",16,9],["cp",17,10],["cp",18,11],["cp",19,12],["cp",10,13],["cp",21,14],["cp",22,15],["cp",23,16],[17,0,37,"diff --git a/welcome.txt b/welcome.txt"],[18,0,28,"index 18832d3..fd3c069 100644"],[19,0,28,"--- a/welcome.txt            "],[20,0,22,"+++ b/welcome.txt      "],[21,0,13,"@@ -1 +1,2 @@ "],[22,0,17," Hello.           "],[23,0,22,"+Nice to meet you.     "],[24,0,8,"bash-3.2$"]],"x":11,"f":[["cp",8,1],["cp",12,5],["cp",5,6],["cp",15,8],["cp",8,9],["cp",18,11],["cp",0,12],["cp",0,13],["cp",21,14],["cp",0,15],["cp",0,16],["cp",0,18],[21,0,12,["a","6"]],[23,0,17,["a","2"]]],"B":[[17,0,37,["a","1"]],[18,0,28,["a","1"]],[19,0,16,["a","1"]],["cp",19,20]],"t":1305092068.13853},{"y":25,"d":[[24,10,"g"]],"x":12,"t":1305092072.56559},{"y":25,"d":[[24,11,"i"]],"x":13,"t":1305092072.66949},{"y":25,"d":[[24,12,"t"]],"x":14,"t":1305092072.77326},{"y":25,"x":15,"t":1305092072.85338},{"y":25,"d":[[24,14,"s"]],"x":16,"t":1305092073.07731},{"y":25,"d":[[24,15,"t"]],"x":17,"t":1305092073.26123},{"y":25,"d":[[24,16,"a"]],"x":18,"t":1305092073.39727},{"y":25,"d":[[24,17,"t"]],"x":19,"t":1305092073.52542},{"y":25,"d":[[24,18,"u"]],"x":20,"t":1305092073.65328},{"y":25,"d":[[24,19,"s"]],"x":21,"t":1305092073.75735},{"y":25,"d":[["cp",1,0],["cp",2,1],["cp",3,2],["cp",4,3],["cp",5,4],["cp",6,5],["cp",7,6],["cp",8,7],["cp",9,8],["cp",10,9],["cp",11,10],["cp",12,11],["cp",9,12],["cp",14,13],["cp",15,14],["cp",16,15],["cp",17,16],["cp",18,17],["cp",19,18],["cp",20,19],["cp",21,20],["cp",22,21],["cp",23,22],["cp",24,23],[24,["a"," "]]],"x":1,"f":[["cp",1,0],["cp",2,1],["cp",5,4],["cp",1,6],["cp",8,7],["cp",1,9],["cp",11,10],["cp",1,11],["cp",14,13],["cp",1,14],["cp",21,20],["cp",1,21],["cp",23,22],["cp",1,23]],"B":[["cp",17,16],["cp",18,17],["cp",19,18],["cp",0,20]],"t":1305092074.04542},{"y":25,"d":[["cp",6,0],["cp",7,1],["cp",8,2],["cp",9,3],["cp",10,4],["cp",11,5],["cp",3,6],["cp",13,7],["cp",14,8],["cp",15,9],["cp",16,10],["cp",17,11],["cp",18,12],["cp",19,13],["cp",20,14],["cp",21,15],["cp",22,16],["cp",23,17],[18,0,17,"# On branch master"],[19,0,25,"# Changes to be committed:"],[20,0,46,"#   (use \"git reset HEAD <file>...\" to unstage)"],[21,0,6,"#      "],[22,0,30,"#       modified:   welcome.txt"],["cp",21,23],[24,0,8,"bash-3.2$"]],"x":11,"f":[["cp",1,0],["cp",7,1],["cp",1,2],["cp",10,4],["cp",0,5],["cp",13,7],["cp",0,8],["cp",0,10],["cp",0,13],["cp",20,14],["cp",22,16],["cp",0,20],[22,0,7,["a","7"]],[22,18,30,["a","2"]]],"B":[["cp",16,10],["cp",17,11],["cp",18,12],["cp",12,13],["cp",0,16],["cp",0,17],["cp",0,18],["cp",0,19]],"t":1305092074.0556},{"y":25,"d":[[24,10,"e"]],"x":12,"t":1305092079.60496},{"y":25,"d":[[24,11,"c"]],"x":13,"t":1305092079.78127},{"y":25,"d":[[24,12,"h"]],"x":14,"t":1305092079.84491},{"y":25,"d":[[24,13,"o"]],"x":15,"t":1305092079.94888},{"y":25,"x":16,"t":1305092080.04498},{"y":25,"d":[[24,15,"B"]],"x":17,"t":1305092080.73322},{"y":25,"d":[[24,16,"y"]],"x":18,"t":1305092080.97286},{"y":25,"d":[[24,17,"e"]],"x":19,"t":1305092081.10902},{"y":25,"d":[[24,18,"-"]],"x":20,"t":1305092081.30897},{"y":25,"d":[[24,19,"B"]],"x":21,"t":1305092081.66906},{"y":25,"d":[[24,20,"y"]],"x":22,"t":1305092081.84475},{"y":25,"d":[[24,21,"e"]],"x":23,"t":1305092081.99668},{"y":25,"d":[[24,22,"."]],"x":24,"t":1305092082.72497},{"y":25,"x":25,"t":1305092082.88481},{"y":25,"d":[[24,24,">"]],"x":26,"t":1305092083.14098},{"y":25,"d":[[24,25,">"]],"x":27,"t":1305092083.31672},{"y":25,"x":28,"t":1305092083.53306},{"y":25,"d":[[24,27,"w"]],"x":29,"t":1305092083.84475},{"y":25,"d":[[24,28,"e"]],"x":30,"t":1305092084.02087},{"y":25,"d":[[24,29,"l"]],"x":31,"t":1305092084.18076},{"y":25,"d":[[24,30,37,"come.txt"]],"x":40,"t":1305092084.58067},{"y":25,"d":[["cp",1,0],["cp",2,1],["cp",3,2],["cp",4,3],["cp",5,4],["cp",2,5],["cp",7,6],["cp",8,7],["cp",9,8],["cp",10,9],["cp",11,10],["cp",12,11],["cp",13,12],["cp",14,13],["cp",15,14],["cp",16,15],["cp",17,16],["cp",18,17],["cp",19,18],["cp",20,19],["cp",21,20],["cp",22,21],["cp",20,22],["cp",24,23],[24,["a"," "]]],"x":1,"f":[["cp",1,0],["cp",3,2],["cp",4,3],["cp",2,4],["cp",7,6],["cp",2,7],["cp",14,13],["cp",2,14],["cp",16,15],["cp",2,16],["cp",22,21],["cp",2,22]],"B":[["cp",10,9],["cp",11,10],["cp",12,11],["cp",0,13]],"t":1305092085.74074},{"y":25,"d":[[24,0,8,"bash-3.2$"]],"x":11,"t":1305092085.74109},{"y":25,"d":[[24,10,"g"]],"x":12,"t":1305092086.54867},{"y":25,"d":[[24,11,"i"]],"x":13,"t":1305092086.64475},{"y":25,"d":[[24,12,"t"]],"x":14,"t":1305092086.75658},{"y":25,"x":15,"t":1305092086.81257},{"y":25,"d":[[24,14,"s"]],"x":16,"t":1305092087.02856},{"y":25,"d":[[24,15,"t"]],"x":17,"t":1305092087.16479},{"y":25,"d":[[24,16,"a"]],"x":18,"t":1305092087.29251},{"y":25,"d":[[24,17,"t"]],"x":19,"t":1305092087.39669},{"y":25,"d":[[24,18,"u"]],"x":20,"t":1305092087.50876},{"y":25,"d":[["cp",16,24]],"x":21,"t":1305092087.58869},{"y":25,"d":[["cp",1,0],["cp",2,1],["cp",3,2],["cp",4,3],["cp",1,4],["cp",6,5],["cp",7,6],["cp",8,7],["cp",9,8],["cp",10,9],["cp",11,10],["cp",12,11],["cp",13,12],["cp",14,13],["cp",15,14],["cp",16,15],["cp",17,16],["cp",18,17],["cp",19,18],["cp",20,19],["cp",21,20],["cp",19,21],["cp",23,22],["cp",15,23],[24,["a"," "]]],"x":1,"f":[["cp",2,1],["cp",3,2],["cp",1,3],["cp",6,5],["cp",1,6],["cp",13,12],["cp",1,13],["cp",15,14],["cp",1,15],["cp",21,20],["cp",1,21]],"B":[["cp",9,8],["cp",10,9],["cp",11,10],["cp",0,12]],"t":1305092087.77246},{"y":25,"d":[["cp",12,0],["cp",13,1],["cp",14,2],["cp",15,3],["cp",16,4],["cp",17,5],["cp",18,6],["cp",19,7],["cp",20,8],["cp",7,9],["cp",22,10],["cp",3,11],["cp",4,12],["cp",5,13],["cp",6,14],["cp",7,15],["cp",8,16],["cp",7,17],[18,2,46,"Changes not staged for commit:               "],[19,4,61,"(use \"git add <file>...\" to update what will be committed)"],[20,4,76,"(use \"git checkout -- <file>...\" to discard changes in working directory)"],["cp",8,22],["cp",7,23],[24,0,8,"bash-3.2$"]],"x":11,"f":[["cp",12,0],["cp",14,2],["cp",1,5],["cp",20,8],["cp",1,12],["cp",1,14],["cp",8,16],["cp",1,20],[22,8,30,["a","1"]]],"B":[["cp",0,8],["cp",0,9],["cp",0,10],["cp",0,11]],"t":1305092087.78176},{"y":25,"d":[[24,10,"g"]],"x":12,"t":1305092090.4689},{"y":25,"d":[[24,11,"i"]],"x":13,"t":1305092090.54869},{"y":25,"d":[[24,12,"t"]],"x":14,"t":1305092090.63632},{"d":[["r","@@ -1 +1,2 @@                                                                   "],["r"," Hello.                                                                         "],["r","+Nice to meet you.                                                              "],["r","bash-3.2$ git status                                                            "],["r","# On branch master                                                              "],["r","# Changes to be committed:                                                      "],["r","#   (use \"git reset HEAD <file>...\" to unstage)                                 "],["r","#                                                                               "],["r","#       modified:   welcome.txt                                                 "],["r","#                                                                               "],["r","bash-3.2$ echo Bye-Bye. >> welcome.txt                                          "],["r","bash-3.2$ git status                                                            "],["r","# On branch master                                                              "],["r","# Changes to be committed:                                                      "],["r","#   (use \"git reset HEAD <file>...\" to unstage)                                 "],["r","#                                                                               "],["r","#       modified:   welcome.txt                                                 "],["r","#                                                                               "],["r","# Changes not staged for commit:                                                "],["r","#   (use \"git add <file>...\" to update what will be committed)                  "],["r","#   (use \"git checkout -- <file>...\" to discard changes in working directory)   "],["r","#                                                                               "],["r","#       modified:   welcome.txt                                                 "],["r","#                                                                               "],["r","bash-3.2$ git                                                                   "]],"x":15,"B":[["a","0"],"d","d","d","d","d","d","d","d","d","d","d","d","d","d","d","d","d","d","d","d","d","d","d","d"],"y":25,"b":[["a","0"],"d","d","d","d","d","d","d","d","d","d","d","d","d","d","d","d","d","d","d","d","d","d","d","d"],"f":[["r","66666666666667777777777777777777777777777777777777777777777777777777777777777777"],["a","7"],["r","22222222222222222277777777777777777777777777777777777777777777777777777777777777"],["a","7"],"d","d","d","d",["r","77777777222222222222222222222227777777777777777777777777777777777777777777777777"],["a","7"],"d","d","d","d","d","d",["r","77777777222222222222222222222227777777777777777777777777777777777777777777777777"],["a","7"],"d","d","d","d",["r","77777777111111111111111111111117777777777777777777777777777777777777777777777777"],["a","7"],"d"],"U":[["a","0"],"d","d","d","d","d","d","d","d","d","d","d","d","d","d","d","d","d","d","d","d","d","d","d","d"],"t":1305092090.7085,"i":1},{"y":25,"d":[[24,14,"s"]],"x":16,"t":1305092090.90045},{"y":25,"d":[[24,15,"t"]],"x":17,"t":1305092091.02038},{"y":25,"d":[[24,16,"a"]],"x":18,"t":1305092091.15651},{"y":25,"d":[[24,17,"t"]],"x":19,"t":1305092091.23631},{"y":25,"d":[[24,18,"u"]],"x":20,"t":1305092091.32451},{"y":25,"d":[["cp",3,24]],"x":21,"t":1305092091.41241},{"y":25,"x":22,"t":1305092091.5488},{"y":25,"d":[[24,21,"="]],"x":23,"t":1305092091.66851},{"y":25,"d":[[24,22,"-"]],"x":24,"t":1305092091.68436},{"y":25,"d":[[24,23,"s"]],"x":25,"t":1305092091.78037},{"y":25,"d":[[24,23," "]],"x":24,"t":1305092092.13242},{"y":25,"d":[[24,22," "]],"x":23,"t":1305092092.30834},{"y":25,"d":[["cp",3,24]],"x":22,"t":1305092092.47652},{"y":25,"d":[[24,21,"-"]],"x":23,"t":1305092092.70038},{"y":25,"d":[[24,22,"0"]],"x":24,"t":1305092092.71751},{"y":25,"d":[[24,23,"s"]],"x":25,"t":1305092092.82026},{"y":25,"d":[[24,23," "]],"x":24,"t":1305092093.19614},{"y":25,"d":[[24,22," "]],"x":23,"t":1305092093.37222},{"y":25,"d":[[24,22,"s"]],"x":24,"t":1305092093.41223},{"y":25,"d":[["cp",1,0],["cp",2,1],["cp",3,2],["cp",4,3],["cp",5,4],["cp",6,5],["cp",7,6],["cp",8,7],["cp",6,8],["cp",10,9],["cp",2,10],["cp",3,11],["cp",4,12],["cp",5,13],["cp",6,14],["cp",7,15],["cp",6,16],["cp",18,17],["cp",19,18],["cp",20,19],["cp",6,20],["cp",7,21],["cp",6,22],["cp",24,23],[24,["a"," "]]],"x":1,"f":[["cp",1,0],["cp",2,1],["cp",0,2],["cp",8,7],["cp",0,8],["cp",7,15],["cp",0,16],["cp",22,21],["cp",0,22]],"t":1305092093.56445},{"y":25,"d":[["cp",1,0],["cp",2,1],["cp",3,2],["cp",4,3],["cp",5,4],["cp",6,5],["cp",7,6],["cp",5,7],["cp",9,8],["cp",1,9],["cp",2,10],["cp",3,11],["cp",4,12],["cp",5,13],["cp",6,14],["cp",5,15],["cp",17,16],["cp",18,17],["cp",19,18],["cp",5,19],["cp",6,20],["cp",5,21],["cp",23,22],[23,0,22,"MM welcome.txt         "],[24,0,8,"bash-3.2$"]],"x":11,"f":[["cp",1,0],["cp",2,1],["cp",7,6],["cp",1,7],["cp",6,14],["cp",1,15],["cp",21,20],["cp",1,21],[23,0,1,"21"]],"t":1305092093.58319},{"y":25,"d":[[24,10,"g"]],"x":12,"t":1305092096.83647},{"y":25,"d":[[24,11,"i"]],"x":13,"t":1305092096.92411},{"y":25,"d":[[24,12,"t"]],"x":14,"t":1305092097.02025},{"y":25,"x":15,"t":1305092097.07735},{"y":25,"d":[[24,14,"d"]],"x":16,"t":1305092097.20413},{"y":25,"d":[[24,15,"i"]],"x":17,"t":1305092097.27598},{"y":25,"d":[[24,16,"f"]],"x":18,"t":1305092097.39634},{"y":25,"d":[[24,17,"f"]],"x":19,"t":1305092097.55698},{"y":25,"d":[["cp",1,0],["cp",2,1],["cp",3,2],["cp",4,3],["cp",5,4],["cp",6,5],["cp",4,6],["cp",8,7],["cp",0,8],["cp",1,9],["cp",2,10],["cp",3,11],["cp",4,12],["cp",5,13],["cp",4,14],["cp",16,15],["cp",17,16],["cp",18,17],["cp",4,18],["cp",5,19],["cp",4,20],["cp",22,21],["cp",23,22],["cp",24,23],[24,["a"," "]]],"x":1,"f":[["cp",1,0],["cp",6,5],["cp",0,6],["cp",5,13],["cp",0,14],["cp",20,19],["cp",0,20],["cp",23,22],["cp",0,23]],"t":1305092097.66791},{"y":25,"d":[["cp",15,7],["cp",16,8],["cp",17,9],["cp",4,10],["cp",5,11],["cp",21,13],["cp",22,14],["cp",23,15],[16,0,61,"diff --git a/welcome.txt b/welcome.txt                        "],[17,0,76,"index fd3c069..51dbfd2 100644                                                "],[18,0,16,"--- a/welcome.txt"],[19,0,30,"+++ b/welcome.txt              "],[20,0,14,"@@ -1,2 +1,3 @@"],[21,0,22," Hello.                "],[22,0,17," Nice to meet you."],[23,0,17,"+Bye-Bye.         "],[24,0,8,"bash-3.2$"]],"x":11,"f":[["cp",19,11],["cp",0,13],["cp",22,14],["cp",0,19],[20,0,14,["a","6"]],["cp",0,22],[23,0,8,["a","2"]]],"B":[[16,0,37,["a","1"]],[17,0,28,["a","1"]],[18,0,16,["a","1"]],["cp",18,19]],"t":1305092097.68074},{"y":25,"d":[[24,10,"g"]],"x":12,"t":1305092101.99607},{"y":25,"d":[[24,11,"i"]],"x":13,"t":1305092102.07631},{"y":25,"d":[[24,12,"t"]],"x":14,"t":1305092102.172},{"y":25,"x":15,"t":1305092102.25988},{"y":25,"d":[[24,14,"d"]],"x":16,"t":1305092102.40388},{"y":25,"d":[[24,15,"i"]],"x":17,"t":1305092102.4919},{"y":25,"d":[[24,16,"f"]],"x":18,"t":1305092102.58009},{"y":25,"d":[["cp",15,24]],"x":19,"t":1305092102.75591},{"y":25,"x":20,"t":1305092102.81185},{"y":25,"d":[[24,19,"H"]],"x":21,"t":1305092103.07608},{"y":25,"d":[[24,20,"E"]],"x":22,"t":1305092103.18787},{"y":25,"d":[[24,21,"A"]],"x":23,"t":1305092103.36371},{"y":25,"d":[[24,22,"D"]],"x":24,"t":1305092103.42767},{"y":25,"d":[["cp",1,0],["cp",2,1],["cp",3,2],["cp",4,3],["cp",5,4],["cp",3,5],["cp",7,6],["cp",8,7],["cp",9,8],["cp",3,9],["cp",4,10],["cp",3,11],["cp",13,12],["cp",14,13],["cp",15,14],["cp",16,15],["cp",17,16],["cp",18,17],["cp",19,18],["cp",20,19],["cp",21,20],["cp",22,21],["cp",23,22],["cp",24,23],[24,["a"," "]]],"x":1,"f":[["cp",5,4],["cp",0,5],["cp",11,10],["cp",0,11],["cp",14,13],["cp",0,14],["cp",20,19],["cp",0,20],["cp",23,22],["cp",0,23]],"B":[["cp",16,15],["cp",17,16],["cp",18,17],["cp",0,19]],"t":1305092103.89171},{"y":25,"d":[["cp",8,0],["cp",3,1],["cp",4,2],["cp",12,4],["cp",13,5],["cp",14,6],["cp",15,7],["cp",16,8],["cp",17,9],["cp",18,10],["cp",19,11],["cp",20,12],["cp",21,13],["cp",22,14],["cp",23,15],["cp",7,16],[17,0,28,"index 18832d3..51dbfd2 100644"],["cp",9,18],["cp",10,19],[20,0,12,"@@ -1 +1,3 @@"],["cp",12,21],[22,1,17,"Nice to meet you."],["cp",14,23],[24,0,8,"bash-3.2$"]],"x":11,"f":[["cp",10,2],["cp",0,4],["cp",13,5],["cp",0,10],["cp",19,11],["cp",0,13],["cp",22,14],["cp",0,19],[20,0,12,["a","6"]],[22,9,17,["a","2"]],["cp",14,23]],"B":[["cp",15,7],["cp",16,8],["cp",17,9],["cp",9,10],["cp",0,15],["cp",7,16],["cp",8,17],["cp",9,19]],"t":1305092103.90446},{"y":25,"d":[[24,10,"g"]],"x":12,"t":1305092104.29182},{"y":25,"d":[[24,11,"i"]],"x":13,"t":1305092104.37209},{"y":25,"d":[[24,12,"t"]],"x":14,"t":1305092104.48348},{"y":25,"x":15,"t":1305092104.52366},{"y":25,"d":[[24,14,"d"]],"x":16,"t":1305092104.68384},{"y":25,"d":[[24,15,"i"]],"x":17,"t":1305092104.75588},{"y":25,"d":[[24,16,"f"]],"x":18,"t":1305092104.87557},{"y":25,"d":[["cp",6,24]],"x":19,"t":1305092105.04367},{"y":25,"x":20,"t":1305092105.17166},{"y":25,"d":[[24,19,"-"]],"x":21,"t":1305092105.65167},{"y":25,"d":[[24,20,"-"]],"x":22,"t":1305092105.83569},{"y":25,"d":[[24,21,"c"]],"x":23,"t":1305092106.00365},{"y":25,"d":[[24,22,"a"]],"x":24,"t":1305092106.12376},{"y":25,"d":[[24,23,"c"]],"x":25,"t":1305092106.26774},{"y":25,"d":[[24,24,"h"]],"x":26,"t":1305092106.35594},{"y":25,"d":[[24,25,"e"]],"x":27,"t":1305092106.49972},{"y":25,"d":[[24,26,"d"]],"x":28,"t":1305092106.67564},{"y":25,"d":[["cp",1,0],["cp",2,1],["cp",0,2],["cp",4,3],["cp",5,4],["cp",6,5],["cp",7,6],["cp",8,7],["cp",9,8],["cp",10,9],["cp",11,10],["cp",12,11],["cp",13,12],["cp",14,13],["cp",15,14],["cp",6,15],["cp",17,16],["cp",8,17],["cp",9,18],["cp",20,19],["cp",11,20],["cp",22,21],["cp",13,22],["cp",24,23],[24,["a"," "]]],"x":1,"f":[["cp",2,1],["cp",0,2],["cp",5,4],["cp",0,5],["cp",11,10],["cp",0,11],["cp",14,13],["cp",0,14],["cp",20,19],["cp",0,20],["cp",22,21],["cp",13,22],["cp",0,23]],"B":[["cp",7,6],["cp",8,7],["cp",9,8],["cp",0,10],["cp",6,15],["cp",7,16],["cp",8,17],["cp",0,19]],"t":1305092107.17189},{"y":25,"d":[["cp",7,0],["cp",8,1],["cp",9,2],["cp",10,3],["cp",11,4],["cp",12,5],["cp",13,6],["cp",14,7],["cp",15,8],["cp",16,9],["cp",1,10],["cp",2,11],["cp",19,12],["cp",4,13],["cp",21,14],["cp",6,15],["cp",23,16],["cp",8,17],[18,0,28,"index 18832d3..fd3c069 100644"],["cp",1,19],["cp",2,20],[21,0,17,"@@ -1 +1,2 @@     "],["cp",4,22],["cp",14,23],[24,0,8,"bash-3.2$"]],"x":11,"f":[["cp",0,1],["cp",10,3],["cp",0,4],["cp",13,6],["cp",0,10],["cp",19,12],["cp",0,13],["cp",21,14],["cp",6,15],["cp",0,19],["cp",12,21],["cp",0,22],["cp",14,23]],"B":[["cp",7,0],["cp",8,1],["cp",1,2],["cp",3,6],["cp",3,7],["cp",15,8],["cp",0,9],["cp",1,10],["cp",1,11],["cp",3,15],["cp",3,16],["cp",8,17],["cp",0,18],["cp",1,19],["cp",1,20]],"t":1305092107.18988},{"y":25,"d":[[24,10,"g"]],"x":12,"t":1305092107.71557},{"y":25,"d":[[24,11,"i"]],"x":13,"t":1305092107.79549},{"y":25,"d":[[24,12,"t"]],"x":14,"t":1305092107.88353},{"y":25,"x":15,"t":1305092107.94774},{"y":25,"d":[[24,14,"c"]],"x":16,"t":1305092108.1235},{"y":25,"d":[[24,15,"o"]],"x":17,"t":1305092108.19547},{"y":25,"d":[[24,16,"m"]],"x":18,"t":1305092108.37977},{"y":25,"d":[[24,17,"m"]],"x":19,"t":1305092108.53941},{"y":25,"d":[[24,18,"i"]],"x":20,"t":1305092108.67585},{"y":25,"d":[[24,19,"t"]],"x":21,"t":1305092108.74747},{"y":25,"x":22,"t":1305092108.85939},{"y":25,"d":[[24,21,"-"]],"x":23,"t":1305092109.18755},{"y":25,"d":[[24,22,"m"]],"x":24,"t":1305092109.46772},{"y":25,"x":25,"t":1305092109.5958},{"y":25,"d":[[24,24,"\""]],"x":26,"t":1305092109.91544},{"y":25,"d":[[24,25,"w"]],"x":27,"t":1305092110.21934},{"y":25,"d":[[24,26,"h"]],"x":28,"t":1305092110.30755},{"y":25,"d":[[24,27,"i"]],"x":29,"t":1305092110.41967},{"y":25,"d":[[24,28,"c"]],"x":30,"t":1305092110.57966},{"y":25,"d":[[24,29,"h"]],"x":31,"t":1305092110.69945},{"y":25,"x":32,"t":1305092110.94732},{"y":25,"d":[[24,31,"v"]],"x":33,"t":1305092111.38747},{"y":25,"d":[[24,32,"e"]],"x":34,"t":1305092111.56336},{"y":25,"d":[[24,33,"r"]],"x":35,"t":1305092111.62756},{"y":25,"d":[[24,34,"s"]],"x":36,"t":1305092111.7713},{"y":25,"d":[[24,35,"i"]],"x":37,"t":1305092111.81947},{"y":25,"d":[[24,36,"o"]],"x":38,"t":1305092111.92341},{"y":25,"d":[[24,37,"n"]],"x":39,"t":1305092112.06732},{"y":25,"x":40,"t":1305092112.29141},{"y":25,"d":[[24,39,"c"]],"x":41,"t":1305092112.69121},{"y":25,"d":[[24,40,"h"]],"x":42,"t":1305092112.79587},{"y":25,"d":[[24,41,"e"]],"x":43,"t":1305092112.92326},{"y":25,"d":[[24,42,"c"]],"x":44,"t":1305092113.0994},{"y":25,"d":[[24,43,"k"]],"x":45,"t":1305092113.17929},{"d":[["r","index fd3c069..51dbfd2 100644                                                   "],["r","--- a/welcome.txt                                                               "],["r","+++ b/welcome.txt                                                               "],["r","@@ -1,2 +1,3 @@                                                                 "],["r"," Hello.                                                                         "],["r"," Nice to meet you.                                                              "],["r","+Bye-Bye.                                                                       "],["r","bash-3.2$ git diff HEAD                                                         "],["r","diff --git a/welcome.txt b/welcome.txt                                          "],["r","index 18832d3..51dbfd2 100644                                                   "],["r","--- a/welcome.txt                                                               "],["r","+++ b/welcome.txt                                                               "],["r","@@ -1 +1,3 @@                                                                   "],["r"," Hello.                                                                         "],["r","+Nice to meet you.                                                              "],["r","+Bye-Bye.                                                                       "],["r","bash-3.2$ git diff --cached                                                     "],["r","diff --git a/welcome.txt b/welcome.txt                                          "],["r","index 18832d3..fd3c069 100644                                                   "],["r","--- a/welcome.txt                                                               "],["r","+++ b/welcome.txt                                                               "],["r","@@ -1 +1,2 @@                                                                   "],["r"," Hello.                                                                         "],["r","+Nice to meet you.                                                              "],["r","bash-3.2$ git commit -m \"which version checke                                   "]],"x":46,"B":[["r","11111111111111111111111111111000000000000000000000000000000000000000000000000000"],["r","11111111111111111000000000000000000000000000000000000000000000000000000000000000"],"d",["a","0"],"d","d","d","d",["r","11111111111111111111111111111111111111000000000000000000000000000000000000000000"],["r","11111111111111111111111111111000000000000000000000000000000000000000000000000000"],["r","11111111111111111000000000000000000000000000000000000000000000000000000000000000"],"d",["a","0"],"d","d","d","d",["r","11111111111111111111111111111111111111000000000000000000000000000000000000000000"],["r","11111111111111111111111111111000000000000000000000000000000000000000000000000000"],["r","11111111111111111000000000000000000000000000000000000000000000000000000000000000"],"d",["a","0"],"d","d","d"],"y":25,"b":[["a","0"],"d","d","d","d","d","d","d","d","d","d","d","d","d","d","d","d","d","d","d","d","d","d","d","d"],"f":[["a","7"],"d","d",["r","66666666666666677777777777777777777777777777777777777777777777777777777777777777"],["a","7"],"d",["r","22222222277777777777777777777777777777777777777777777777777777777777777777777777"],["a","7"],"d","d","d","d",["r","66666666666667777777777777777777777777777777777777777777777777777777777777777777"],["a","7"],["r","22222222222222222277777777777777777777777777777777777777777777777777777777777777"],["r","22222222277777777777777777777777777777777777777777777777777777777777777777777777"],["a","7"],"d","d","d","d",["r","66666666666667777777777777777777777777777777777777777777777777777777777777777777"],["a","7"],["r","22222222222222222277777777777777777777777777777777777777777777777777777777777777"],["a","7"]],"U":[["a","0"],"d","d","d","d","d","d","d","d","d","d","d","d","d","d","d","d","d","d","d","d","d","d","d","d"],"t":1305092113.41155,"i":1},{"y":25,"d":[[24,45,"d"]],"x":47,"t":1305092113.57947},{"y":25,"x":48,"t":1305092113.7394},{"y":25,"d":[[24,47,"i"]],"x":49,"t":1305092113.89128},{"y":25,"d":[[24,48,"n"]],"x":50,"t":1305092114.03516},{"y":25,"d":[[24,49,"?"]],"x":51,"t":1305092114.5074},{"y":25,"d":[[24,50,"\""]],"x":52,"t":1305092114.89937},{"y":25,"d":[["cp",1,0],["cp",2,1],["cp",3,2],["cp",4,3],["cp",5,4],["cp",6,5],["cp",7,6],["cp",8,7],["cp",9,8],["cp",0,9],["cp",1,10],["cp",12,11],["cp",3,12],["cp",14,13],["cp",5,14],["cp",16,15],["cp",7,16],["cp",18,17],["cp",0,18],["cp",1,19],["cp",21,20],["cp",3,21],["cp",13,22],["cp",24,23],[24,["a"," "]]],"x":1,"f":[["cp",3,2],["cp",0,3],["cp",6,5],["cp",0,6],["cp",12,11],["cp",0,12],["cp",14,13],["cp",5,14],["cp",0,15],["cp",11,20],["cp",0,21],["cp",13,22],["cp",0,23]],"B":[["cp",1,0],["cp",3,2],["cp",8,7],["cp",9,8],["cp",0,9],["cp",2,11],["cp",7,16],["cp",8,17],["cp",0,18],["cp",2,20]],"t":1305092115.63528},{"y":25,"d":[["cp",1,0],["cp",2,1],["cp",3,2],["cp",4,3],["cp",5,4],["cp",6,5],["cp",7,6],["cp",8,7],["cp",9,8],["cp",0,9],["cp",11,10],["cp",2,11],["cp",13,12],["cp",4,13],["cp",15,14],["cp",6,15],["cp",17,16],["cp",8,17],["cp",0,18],["cp",20,19],["cp",2,20],["cp",12,21],["cp",23,22],[23,0,50,"[master 0e3a4c9] which version checked in?         "]],"x":1,"f":[["cp",2,1],["cp",0,2],["cp",5,4],["cp",0,5],["cp",11,10],["cp",0,11],["cp",13,12],["cp",4,13],["cp",0,14],["cp",10,19],["cp",0,20],["cp",12,21],["cp",0,22]],"B":[["cp",2,1],["cp",7,6],["cp",8,7],["cp",0,8],["cp",1,10],["cp",6,15],["cp",7,16],["cp",0,17],["cp",1,19]],"t":1305092115.92652},{"y":25,"d":[["cp",1,0],["cp",2,1],["cp",3,2],["cp",4,3],["cp",5,4],["cp",6,5],["cp",7,6],["cp",8,7],["cp",9,8],["cp",10,9],["cp",1,10],["cp",12,11],["cp",3,12],["cp",14,13],["cp",5,14],["cp",16,15],["cp",7,16],["cp",8,17],["cp",19,18],["cp",1,19],["cp",11,20],["cp",22,21],["cp",23,22],[23,0,48," 1 files changed, 1 insertions(+), 0 deletions(-)"],[24,0,8,"bash-3.2$"]],"x":11,"f":[["cp",1,0],["cp",2,1],["cp",4,3],["cp",1,4],["cp",10,9],["cp",1,10],["cp",12,11],["cp",3,12],["cp",1,13],["cp",9,18],["cp",1,19],["cp",11,20],["cp",1,21]],"B":[["cp",1,0],["cp",6,5],["cp",7,6],["cp",8,7],["cp",0,9],["cp",5,14],["cp",6,15],["cp",7,16],["cp",0,18]],"t":1305092115.92811},{"y":25,"d":[[24,10,"g"]],"x":12,"t":1305092116.89095},{"y":25,"d":[[24,11,"i"]],"x":13,"t":1305092116.97109},{"y":25,"d":[[24,12,"t"]],"x":14,"t":1305092117.1152},{"y":25,"x":15,"t":1305092117.1872},{"y":25,"d":[[24,14,"l"]],"x":16,"t":1305092117.45921},{"y":25,"d":[[24,15,"o"]],"x":17,"t":1305092117.63509},{"y":25,"d":[[24,16,"g"]],"x":18,"t":1305092117.74831},{"y":25,"x":19,"t":1305092117.83527},{"y":25,"d":[[24,18,"-"]],"x":20,"t":1305092118.0192},{"y":25,"d":[[24,19,"-"]],"x":21,"t":1305092118.20304},{"y":25,"d":[[24,20,"o"]],"x":22,"t":1305092118.84301},{"y":25,"d":[[24,21,"n"]],"x":23,"t":1305092118.97887},{"y":25,"d":[[24,22,"e"]],"x":24,"t":1305092119.05905},{"y":25,"d":[[24,23,"l"]],"x":25,"t":1305092119.16339},{"y":25,"d":[[24,24,"i"]],"x":26,"t":1305092119.3231},{"y":25,"d":[[24,25,"n"]],"x":27,"t":1305092119.43483},{"y":25,"d":[[24,26,"e"]],"x":28,"t":1305092119.54741},{"y":25,"x":29,"t":1305092119.64301},{"y":25,"d":[[24,28,"-"]],"x":30,"t":1305092120.31496},{"y":25,"d":[[24,29,"-"]],"x":31,"t":1305092120.49896},{"y":25,"d":[[24,30,"s"]],"x":32,"t":1305092120.65085},{"y":25,"d":[[24,31,"t"]],"x":33,"t":1305092120.74699},{"y":25,"d":[[24,32,"a"]],"x":34,"t":1305092120.86669},{"y":25,"d":[[24,33,"t"]],"x":35,"t":1305092120.97878},{"y":25,"d":[["cp",1,0],["cp",2,1],["cp",3,2],["cp",4,3],["cp",5,4],["cp",6,5],["cp",7,6],["cp",8,7],["cp",9,8],["cp",0,9],["cp",11,10],["cp",2,11],["cp",13,12],["cp",4,13],["cp",15,14],["cp",6,15],["cp",7,16],["cp",18,17],["cp",0,18],["cp",10,19],["cp",21,20],["cp",22,21],["cp",23,22],["cp",24,23],[24,["a"," "]]],"x":1,"f":[["cp",1,0],["cp",3,2],["cp",0,3],["cp",9,8],["cp",0,9],["cp",11,10],["cp",2,11],["cp",0,12],["cp",8,17],["cp",0,18],["cp",10,19],["cp",0,20]],"B":[["cp",5,4],["cp",6,5],["cp",7,6],["cp",0,8],["cp",4,13],["cp",5,14],["cp",6,15],["cp",0,17]],"t":1305092121.20287},{"y":25,"d":[["cp",7,0],["cp",8,1],["cp",9,2],["cp",10,3],["cp",11,4],["cp",12,5],["cp",13,6],["cp",14,7],["cp",15,8],["cp",0,9],["cp",17,10],["cp",2,11],["cp",3,12],["cp",20,13],["cp",21,14],["cp",22,15],["cp",23,16],[17,0,32,"0e3a4c9 which version checked in?"],[18,1,13,"welcome.txt |"],[18,18,20,"1 +"],["cp",15,19],[20,0,50,"61b1516 who does commit?                           "],[21,0,41,"3869015 intialized.                       "],["cp",18,22],["cp",15,23],[24,0,8,"bash-3.2$"]],"x":11,"f":[["cp",8,1],["cp",0,2],["cp",10,3],["cp",11,4],["cp",0,8],["cp",1,10],["cp",0,11],["cp",3,12],[17,0,12,"3333333777777"],[18,20,"2"],["cp",0,19],["cp",17,20],["cp",17,21],["cp",18,22]],"B":[["cp",6,0],["cp",1,4],["cp",1,5],["cp",13,6],["cp",14,7],["cp",0,8],["cp",0,9],["cp",1,13],["cp",1,14],["cp",1,15],["cp",1,16]],"t":1305092121.21707},{"y":25,"d":[[24,10,"g"]],"x":12,"t":1305092125.57857},{"y":25,"d":[[24,11,"i"]],"x":13,"t":1305092125.66673},{"y":25,"d":[[24,12,"t"]],"x":14,"t":1305092125.76283},{"y":25,"x":15,"t":1305092125.83464},{"y":25,"d":[[24,14,"s"]],"x":16,"t":1305092125.98735},{"y":25,"d":[[24,15,"t"]],"x":17,"t":1305092126.09855},{"y":25,"d":[[24,16,"a"]],"x":18,"t":1305092126.22661},{"y":25,"d":[[24,17,"t"]],"x":19,"t":1305092126.32322},{"y":25,"d":[[24,18,"u"]],"x":20,"t":1305092126.43493},{"y":25,"d":[[24,19,"s"]],"x":21,"t":1305092126.51475},{"y":25,"x":22,"t":1305092126.68255},{"y":25,"d":[[24,21,"-"]],"x":23,"t":1305092126.82656},{"y":25,"d":[[24,22,"s"]],"x":24,"t":1305092126.93858},{"y":25,"d":[["cp",1,0],["cp",2,1],["cp",3,2],["cp",4,3],["cp",5,4],["cp",6,5],["cp",7,6],["cp",8,7],["cp",9,8],["cp",10,9],["cp",1,10],["cp",2,11],["cp",13,12],["cp",14,13],["cp",15,14],["cp",16,15],["cp",17,16],["cp",18,17],["cp",14,18],["cp",20,19],["cp",21,20],["cp",17,21],["cp",14,22],["cp",24,23],[24,["a"," "]]],"x":1,"f":[["cp",1,0],["cp",2,1],["cp",3,2],["cp",4,3],["cp",1,4],["cp",0,9],["cp",1,10],["cp",2,11],["cp",1,12],["cp",17,16],["cp",18,17],["cp",1,18],["cp",16,19],["cp",17,21],["cp",1,22]],"B":[["cp",1,0],["cp",6,5],["cp",7,6],["cp",8,7],["cp",0,9]],"t":1305092127.04269},{"y":25,"d":[["cp",1,0],["cp",2,1],["cp",3,2],["cp",4,3],["cp",5,4],["cp",6,5],["cp",7,6],["cp",8,7],["cp",9,8],["cp",0,9],["cp",1,10],["cp",12,11],["cp",13,12],["cp",14,13],["cp",15,14],["cp",16,15],["cp",17,16],["cp",13,17],["cp",19,18],["cp",20,19],["cp",16,20],["cp",13,21],["cp",23,22],[23,0,22," M welcome.txt         "],[24,0,8,"bash-3.2$"]],"x":11,"f":[["cp",1,0],["cp",2,1],["cp",3,2],["cp",0,3],["cp",9,8],["cp",0,9],["cp",1,10],["cp",0,11],["cp",16,15],["cp",17,16],["cp",0,17],["cp",15,18],["cp",16,20],["cp",0,21],[23,1,"1"]],"B":[["cp",5,4],["cp",6,5],["cp",7,6],["cp",0,8]],"t":1305092127.05097},{"y":25,"d":[[24,10,"g"]],"x":12,"t":1305092128.78762},{"y":25,"d":[[24,11,"i"]],"x":13,"t":1305092128.85059},{"y":25,"d":[[24,12,"t"]],"x":14,"t":1305092128.97871},{"y":25,"x":15,"t":1305092129.05058},{"y":25,"d":[[24,14,"d"]],"x":16,"t":1305092129.20239},{"y":25,"d":[[24,15,"i"]],"x":17,"t":1305092129.27438},{"y":25,"d":[[24,16,"f"]],"x":18,"t":1305092129.38659},{"y":25,"d":[[24,17,"f"]],"x":19,"t":1305092129.56245},{"y":25,"d":[["cp",1,0],["cp",2,1],["cp",3,2],["cp",4,3],["cp",5,4],["cp",6,5],["cp",7,6],["cp",8,7],["cp",9,8],["cp",0,9],["cp",11,10],["cp",12,11],["cp",13,12],["cp",14,13],["cp",15,14],["cp",16,15],["cp",12,16],["cp",18,17],["cp",19,18],["cp",15,19],["cp",12,20],["cp",22,21],["cp",23,22],["cp",24,23],[24,["a"," "]]],"x":1,"f":[["cp",1,0],["cp",2,1],["cp",3,2],["cp",8,7],["cp",2,8],["cp",0,9],["cp",2,10],["cp",15,14],["cp",16,15],["cp",2,16],["cp",14,17],["cp",15,19],["cp",2,20],["cp",23,22],["cp",2,23]],"B":[["cp",4,3],["cp",5,4],["cp",6,5],["cp",0,7]],"t":1305092130.25061},{"y":25,"d":[["cp",8,0],["cp",9,1],["cp",10,2],["cp",11,3],["cp",12,4],["cp",13,5],["cp",14,6],["cp",15,7],["cp",4,8],["cp",17,9],["cp",18,10],["cp",7,11],["cp",21,13],["cp",22,14],["cp",23,15],[16,0,48,"diff --git a/welcome.txt b/welcome.txt           "],[17,0,28,"index fd3c069..51dbfd2 100644"],[18,0,18,"--- a/welcome.txt  "],[19,0,20,"+++ b/welcome.txt    "],[20,0,48,"@@ -1,2 +1,3 @@                                  "],["cp",0,21],[22,1,17,"Nice to meet you."],[23,0,17,"+Bye-Bye.         "],[24,0,8,"bash-3.2$"]],"x":11,"f":[["cp",2,0],["cp",9,1],["cp",14,6],["cp",15,7],["cp",6,9],["cp",6,10],["cp",7,11],["cp",22,14],["cp",0,15],["cp",0,17],["cp",0,18],["cp",0,19],[20,0,14,["a","6"]],["cp",0,22],[23,0,8,["a","2"]]],"B":[["cp",0,3],["cp",0,4],["cp",0,5],["cp",0,6],[16,0,37,["a","1"]],[17,0,28,["a","1"]],[18,0,16,["a","1"]],["cp",18,19]],"t":1305092130.26254},{"y":25,"d":[[24,10,"e"]],"x":12,"t":1305092132.18645},{"y":25,"d":[[24,11,"x"]],"x":13,"t":1305092132.35432},{"y":25,"d":[[24,12,"i"]],"x":14,"t":1305092132.49858},{"y":25,"d":[[24,13,"t"]],"x":15,"t":1305092132.61041},{"y":25,"d":[["cp",1,0],["cp",2,1],["cp",3,2],["cp",4,3],["cp",5,4],["cp",6,5],["cp",7,6],["cp",3,7],["cp",9,8],["cp",10,9],["cp",6,10],["cp",3,11],["cp",13,12],["cp",14,13],["cp",15,14],["cp",16,15],["cp",17,16],["cp",18,17],["cp",19,18],["cp",20,19],["cp",21,20],["cp",22,21],["cp",23,22],["cp",24,23],[24,["a"," "]]],"x":1,"f":[["cp",1,0],["cp",2,1],["cp",6,5],["cp",7,6],["cp",1,7],["cp",5,8],["cp",6,10],["cp",1,11],["cp",14,13],["cp",1,14],["cp",20,19],["cp",1,20],["cp",23,22],["cp",1,23]],"B":[["cp",16,15],["cp",17,16],["cp",18,17],["cp",0,19]],"t":1305092132.77026},{"y":25,"d":[["cp",1,0],["cp",2,1],["cp",3,2],["cp",4,3],["cp",5,4],["cp",6,5],["cp",2,6],["cp",8,7],["cp",9,8],["cp",5,9],["cp",2,10],["cp",12,11],["cp",13,12],["cp",14,13],["cp",15,14],["cp",16,15],["cp",17,16],["cp",18,17],["cp",19,18],["cp",20,19],["cp",21,20],["cp",22,21],["cp",23,22],[23,0,13,"exit          "]],"x":1,"f":[["cp",1,0],["cp",5,4],["cp",6,5],["cp",0,6],["cp",4,7],["cp",5,9],["cp",0,10],["cp",13,12],["cp",0,13],["cp",19,18],["cp",0,19],["cp",22,21],["cp",0,22]],"B":[["cp",15,14],["cp",16,15],["cp",17,16],["cp",0,18]],"t":1305092132.77051}]}